mcp_server_opendal/__init__.py
mcp_server_opendal/resource.py
mcp_server_opendal/server.py
mcp_server_opendal-0.2.0.dist-info/METADATA
mcp_server_opendal-0.2.0.dist-info/WHEEL
mcp_server_opendal-0.2.0.dist-info/entry_points.txt
mcp_server_opendal-0.2.0.dist-info/licenses/LICENSE
mcp_server_opendal-0.2.0.dist-info/RECORD
